{
    "$schema": "https://schema.management.azure.com/schemas/2019-04-01/deploymentParameters.json#",
    "contentVersion": "1.0.0.0",
    "parameters": {
        "serviceName": {
            "value": "## DEFINE ##"
        },
        "sqlAdminPassword": {
            "value": "## TO BE DEFINED ##"
        },
        "isSecondary": {
            "value": false
        },
        "appServicePlanName": {
            "value": ""
        },
        "securityAuthenticationAuthority": {
            "value": ""
        },
        "securityAuthenticationAudience": {
            "value": ""
        },
        "enableAadSmartOnFhirProxy": {
            "value": false
        },
        "deployApplicationInsights": {
            "value": true
        },
        "applicationInsightsLocation": {
            "value": "eastus"
        },
        "additionalFhirServerConfigProperties": {
            "value": {}
        },
        "fhirVersion": {
            "value": "R4"
        },
        "enableExport": {
            "value": false
        },
        "resourceTags": {
            "value": {
                "Environment": "Prod",
                "Project": "FHIR Server"
            }
        }
    }
}